{
  "name": "metallics_arts:cadmium_base/arena_pool",
  "fallback": "minecraft:empty",
  "elements": [
    {
      "weight": 2,
      "element": {
        "location": "metallics_arts:cadmium_base/arena/arena",
        "processors": "minecraft:empty",
        "projection": "rigid",
        "element_type": "minecraft:single_pool_element"
      }
    },
    {
      "weight": 4,
      "element": {
        "location": "metallics_arts:cadmium_base/arena/arena_alt",
        "processors": "minecraft:empty",
        "projection": "rigid",
        "element_type": "minecraft:single_pool_element"
      }
    }
  ]
}